JT_Selenium/__init__.py
JT_Selenium/captcha.py
JT_Selenium/chrome_urls.py
JT_Selenium/util.py
JT_Selenium-0.0.10.dist-info/LICENSE
JT_Selenium-0.0.10.dist-info/METADATA
JT_Selenium-0.0.10.dist-info/WHEEL
JT_Selenium-0.0.10.dist-info/top_level.txt
JT_Selenium-0.0.10.dist-info/RECORD
