Metadata-Version: 2.1
Name: JT-Selenium
Version: 0.0.10
Summary: My Selenium API Wrapper/Utility
Home-page: https://github.com/Gothingbop/JT_Selenium
Author: Jacob Thompson
Author-email: Gothingbop@gmail.com
License: UNKNOWN
Platform: UNKNOWN
Classifier: Programming Language :: Python :: 3
Classifier: License :: OSI Approved :: MIT License
Classifier: Operating System :: OS Independent
Requires-Python: >=3
Requires-Dist: selenium
Requires-Dist: requests
